lgenome/__init__.py
lgenome/manager.py
lgenome-0.1.0.dist-info/METADATA
lgenome-0.1.0.dist-info/WHEEL
lgenome-0.1.0.dist-info/top_level.txt
lgenome-0.1.0.dist-info/RECORD
